{
  "dockerhub": {
    "web_url": "https://hub.docker.com/r/mafrosis/rpi-memcached",
    "repository_url": "https://hub.docker.com/v2/repositories/mafrosis/rpi-memcached",
    "tags_url": "https://hub.docker.com/v2/repositories/mafrosis/rpi-memcached/tags",
    "dockerfile_url": "https://hub.docker.com/v2/repositories/mafrosis/rpi-memcached/dockerfile",
    "autobuild_url": "https://hub.docker.com/v2/repositories/mafrosis/rpi-memcached/autobuild",
    "user": "mafrosis",
    "name": "rpi-memcached",
    "namespace": "mafrosis",
    "status": 1,
    "is_private": false,
    "is_automated": true,
    "star_count": 0,
    "pull_count": 34,
    "last_updated": "2016-08-03T13:25:22.967464Z",
    "permissions": {
      "read": true,
      "write": false,
      "admin": false
    },
    "tags": [
      {
        "name": "latest",
        "full_size": 50000488,
        "id": 4131677,
        "repository": 834792,
        "creator": 447743,
        "last_updater": 447743,
        "last_updated": "2016-08-03T13:25:22.635083Z",
        "image_id": null,
        "v2": true,
        "platforms": [
          16
        ]
      }
    ],
    "build_name": "mafrosis/rpi-memcached"
  },
  "name": "mafrosis/rpi-memcached Docker container",
  "description": "RPi-compatible memcached",
  "readme": null,
  "dockerfile": "",
  "dockerfile_json": {
    "add": [],
    "expose": [],
    "volume": [],
    "run": [],
    "workdir": []
  },
  "source_repository_url": "https://github.com/mafrosis/rpi-memcached.git",
  "source_repository_type": "git",
  "source_repository_provider": "github",
  "source_repository_web_url": "https://github.com/mafrosis/rpi-memcached",
  "docker_repository": "mafrosis/rpi-memcached",
  "docker_image": "mafrosis/rpi-memcached",
  "parameters_schema": {
    "exposed_ports": {
      "default": [],
      "type": "json_array"
    }
  },
  "type": "docker",
  "docker_name": "mafrosis/rpi-memcached",
  "revision": "latest",
  "uris": [
    "https://hub.docker.com/r/mafrosis/rpi-memcached",
    "https://hub.docker.com/v2/repositories/mafrosis/rpi-memcached",
    "https://github.com/mafrosis/rpi-memcached.git"
  ],
  "labels": [
    "Docker",
    "Type/Infrastructure/Operating System",
    "Type/Middleware/Cache/Memcached"
  ],
  "info_url": "https://hub.docker.com/r/mafrosis/rpi-memcached",
  "requires": [
    {
      "kind": "host",
      "label": "Docker Engine"
    }
  ],
  "latest": true,
  "gatherbase_origin": "docker-hub"
}