{
  "dockerhub": {
    "web_url": "https://hub.docker.com/r/merapar/logstash-docker",
    "repository_url": "https://hub.docker.com/v2/repositories/merapar/logstash-docker",
    "tags_url": "https://hub.docker.com/v2/repositories/merapar/logstash-docker/tags",
    "dockerfile_url": "https://hub.docker.com/v2/repositories/merapar/logstash-docker/dockerfile",
    "autobuild_url": "https://hub.docker.com/v2/repositories/merapar/logstash-docker/autobuild",
    "user": "merapar",
    "name": "logstash-docker",
    "namespace": "merapar",
    "status": 1,
    "is_private": false,
    "is_automated": true,
    "star_count": 0,
    "pull_count": 1514,
    "last_updated": "2016-10-14T17:40:10.736403Z",
    "permissions": {
      "read": true,
      "write": false,
      "admin": false
    },
    "tags": [
      {
        "name": "latest",
        "full_size": 202441388,
        "id": 1495647,
        "repository": 434433,
        "creator": 523640,
        "last_updater": 523642,
        "last_updated": "2016-10-14T17:40:08.628478Z",
        "image_id": null,
        "v2": true,
        "platforms": [
          5
        ]
      },
      {
        "name": "2.2",
        "full_size": 201852458,
        "id": 2500917,
        "repository": 434433,
        "creator": 523642,
        "last_updater": 523642,
        "last_updated": "2016-04-01T07:54:37.705678Z",
        "image_id": null,
        "v2": true,
        "platforms": []
      }
    ],
    "build_name": "merapar/logstash-docker"
  },
  "name": "merapar/logstash-docker Docker container",
  "description": "Logstash docker reading from RabbitMQ, pushing to ElasticSearch",
  "readme": null,
  "dockerfile": "FROM          logstash:2.2\nMAINTAINER    Merapar\nADD           logstash.conf /opt/logstash/logstash.conf\nCMD           logstash -f /opt/logstash/logstash.conf\n",
  "dockerfile_json": {
    "add": [
      {
        "source": "",
        "dest": ""
      }
    ],
    "expose": [],
    "volume": [],
    "run": [],
    "workdir": [],
    "from": "         logstash:2.2",
    "maintainer": "   Merapar",
    "cmd": "          logstash -f /opt/logstash/logstash.conf"
  },
  "source_repository_url": "https://github.com/merapar/logstash-docker.git",
  "source_repository_type": "git",
  "source_repository_provider": "github",
  "source_repository_web_url": "https://github.com/merapar/logstash-docker",
  "docker_repository": "merapar/logstash-docker",
  "docker_image": "merapar/logstash-docker",
  "parameters_schema": {
    "exposed_ports": {
      "default": [],
      "type": "json_array"
    }
  },
  "type": "docker",
  "docker_name": "merapar/logstash-docker",
  "revision": "latest",
  "uris": [
    "https://hub.docker.com/r/merapar/logstash-docker",
    "https://hub.docker.com/v2/repositories/merapar/logstash-docker",
    "https://github.com/merapar/logstash-docker.git"
  ],
  "labels": [
    "Docker",
    "Binding/Region/North America/US",
    "Type/Devopsware/Logging/Logstash",
    "Type/Middleware/Messaging/RabbitMQ",
    "Type/Middleware/Search/Elasticsearch"
  ],
  "info_url": "https://hub.docker.com/r/merapar/logstash-docker",
  "requires": [
    {
      "kind": "host",
      "label": "Docker Engine"
    }
  ],
  "latest": true,
  "gatherbase_origin": "docker-hub"
}