{
  "dockerhub": {
    "web_url": "https://hub.docker.com/r/_/sonarqube",
    "repository_url": "https://hub.docker.com/v2/repositories/library/sonarqube",
    "tags_url": "https://hub.docker.com/v2/repositories/library/sonarqube/tags",
    "user": "library",
    "name": "sonarqube",
    "namespace": "library",
    "status": 1,
    "is_private": false,
    "is_automated": false,
    "star_count": 355,
    "pull_count": 1012984,
    "last_updated": "2016-10-11T20:34:36.309078Z",
    "permissions": {
      "read": true,
      "write": false,
      "admin": false
    },
    "tags": [
      {
        "name": "6.1-alpine",
        "full_size": 182155612,
        "id": 5383503,
        "repository": 208233,
        "creator": 621950,
        "last_updater": 621950,
        "last_updated": "2016-10-11T20:34:36.040552Z",
        "image_id": null,
        "v2": true,
        "platforms": [
          5
        ]
      },
      {
        "name": "alpine",
        "full_size": 182155612,
        "id": 4215591,
        "repository": 208233,
        "creator": 621950,
        "last_updater": 621950,
        "last_updated": "2016-10-11T20:34:27.404781Z",
        "image_id": null,
        "v2": true,
        "platforms": [
          5
        ]
      },
      {
        "name": "6.1",
        "full_size": 369354247,
        "id": 5383486,
        "repository": 208233,
        "creator": 621950,
        "last_updater": 621950,
        "last_updated": "2016-10-11T20:34:16.188517Z",
        "image_id": null,
        "v2": true,
        "platforms": [
          5
        ]
      },
      {
        "name": "latest",
        "full_size": 369354247,
        "id": 170541,
        "repository": 208233,
        "creator": 7,
        "last_updater": 621950,
        "last_updated": "2016-10-11T20:34:06.279645Z",
        "image_id": null,
        "v2": true,
        "platforms": [
          5
        ]
      },
      {
        "name": "5.6.3-alpine",
        "full_size": 172667699,
        "id": 5260608,
        "repository": 208233,
        "creator": 621950,
        "last_updater": 621950,
        "last_updated": "2016-10-11T20:33:55.576263Z",
        "image_id": null,
        "v2": true,
        "platforms": [
          5
        ]
      },
      {
        "name": "lts-alpine",
        "full_size": 172667699,
        "id": 3805020,
        "repository": 208233,
        "creator": 621950,
        "last_updater": 621950,
        "last_updated": "2016-10-11T20:33:46.394318Z",
        "image_id": null,
        "v2": true,
        "platforms": [
          5
        ]
      },
      {
        "name": "5.6.3",
        "full_size": 359865447,
        "id": 5260583,
        "repository": 208233,
        "creator": 621950,
        "last_updater": 621950,
        "last_updated": "2016-10-11T20:33:36.462003Z",
        "image_id": null,
        "v2": true,
        "platforms": [
          5
        ]
      },
      {
        "name": "lts",
        "full_size": 359865447,
        "id": 170531,
        "repository": 208233,
        "creator": 7,
        "last_updater": 621950,
        "last_updated": "2016-10-11T20:33:26.701339Z",
        "image_id": null,
        "v2": true,
        "platforms": [
          5
        ]
      },
      {
        "name": "6.0",
        "full_size": 368241869,
        "id": 4220225,
        "repository": 208233,
        "creator": 621950,
        "last_updater": 621950,
        "last_updated": "2016-10-05T22:55:06.639848Z",
        "image_id": null,
        "v2": true,
        "platforms": [
          5
        ]
      },
      {
        "name": "6.0-alpine",
        "full_size": 181046670,
        "id": 4220256,
        "repository": 208233,
        "creator": 621950,
        "last_updater": 621950,
        "last_updated": "2016-10-05T20:23:52.020383Z",
        "image_id": null,
        "v2": true,
        "platforms": [
          5
        ]
      }
    ]
  },
  "docker_image": "sonarqube",
  "name": "sonarqube Docker container",
  "description": "SonarQube is an open source platform for continuous inspection of code quality.",
  "readme": "# Supported tags and respective `Dockerfile` links\n\n-\t[`latest`, `6.1` (*6.1/Dockerfile*)](https://github.com/SonarSource/docker-sonarqube/blob/d73a971436d36a56f53145aa3490ad9addfc4ec6/6.1/Dockerfile)\n-\t[`lts`, `5.6.3` (*5.6.3/Dockerfile*)](https://github.com/SonarSource/docker-sonarqube/blob/d73a971436d36a56f53145aa3490ad9addfc4ec6/5.6.3/Dockerfile)\n-\t[`alpine`, `6.1-alpine` (*6.1-alpine/Dockerfile*)](https://github.com/SonarSource/docker-sonarqube/blob/d73a971436d36a56f53145aa3490ad9addfc4ec6/6.1-alpine/Dockerfile)\n-\t[`lts-alpine`, `5.6.3-alpine` (*5.6.3-alpine/Dockerfile*)](https://github.com/SonarSource/docker-sonarqube/blob/d73a971436d36a56f53145aa3490ad9addfc4ec6/5.6.3-alpine/Dockerfile)\n\nFor more information about this image and its history, please see [the relevant manifest file (`library/sonarqube`)](https://github.com/docker-library/official-images/blob/master/library/sonarqube). This image is updated via [pull requests to the `docker-library/official-images` GitHub repo](https://github.com/docker-library/official-images/pulls?q=label%3Alibrary%2Fsonarqube).\n\nFor detailed information about the virtual/transfer sizes and individual layers of each of the above supported tags, please see [the `repos/sonarqube/tag-details.md` file](https://github.com/docker-library/repo-info/blob/master/repos/sonarqube/tag-details.md) in [the `docker-library/repo-info` GitHub repo](https://github.com/docker-library/repo-info).\n\n# What is SonarQube?\n\nSonarQube is an open source platform for continuous inspection of code quality.\n\n> [wikipedia.org/wiki/SonarQube](http://en.wikipedia.org/wiki/SonarQube)\n\n![logo](https://raw.githubusercontent.com/docker-library/docs/84479f149eb7d748d5dc057665eb96f923e60dc1/sonarqube/logo.png)\n\n# How to use this image\n\n## Run SonarQube\n\nThe server is started this way:\n\n```console\n$ docker run -d --name sonarqube -p 9000:9000 -p 9092:9092 sonarqube\n```\n\nTo analyse a project:\n\n```console\n$ On Linux:\nmvn sonar:sonar\n\n$ With boot2docker:\nmvn sonar:sonar -Dsonar.host.url=http://$(boot2docker ip):9000 -Dsonar.jdbc.url=\"jdbc:h2:tcp://$(boot2docker ip)/sonar\"\n```\n\n## Database configuration\n\nBy default, the image will use an embedded H2 database that is not suited for production.\n\nThe production database is configured with these variables: `SONARQUBE_JDBC_USERNAME`, `SONARQUBE_JDBC_PASSWORD` and `SONARQUBE_JDBC_URL`.\n\n```console\n$ docker run -d --name sonarqube \\\n\t-p 9000:9000 -p 9092:9092 \\\n\t-e SONARQUBE_JDBC_USERNAME=sonar \\\n\t-e SONARQUBE_JDBC_PASSWORD=sonar \\\n\t-e SONARQUBE_JDBC_URL=jdbc:postgresql://localhost/sonar \\\n\tsonarqube\n```\n\nMore recipes can be found [here](https://github.com/SonarSource/docker-sonarqube/blob/master/recipes.md).\n\n## Administration\n\nThe administration guide can be found [here](http://docs.sonarqube.org/display/SONAR/Administration+Guide).\n\n# Image Variants\n\nThe `sonarqube` images come in many flavors, each designed for a specific use case.\n\n## `sonarqube:<version>`\n\nThis is the defacto image. If you are unsure about what your needs are, you probably want to use this one. It is designed to be used both as a throw away container (mount your source code and start the container to start your app), as well as the base to build other images off of.\n\n## `sonarqube:alpine`\n\nThis image is based on the popular [Alpine Linux project](http://alpinelinux.org), available in [the `alpine` official image](https://hub.docker.com/_/alpine). Alpine Linux is much smaller than most distribution base images (~5MB), and thus leads to much slimmer images in general.\n\nThis variant is highly recommended when final image size being as small as possible is desired. The main caveat to note is that it does use [musl libc](http://www.musl-libc.org) instead of [glibc and friends](http://www.etalabs.net/compare_libcs.html), so certain software might run into issues depending on the depth of their libc requirements. However, most software doesn't have an issue with this, so this variant is usually a very safe choice. See [this Hacker News comment thread](https://news.ycombinator.com/item?id=10782897) for more discussion of the issues that might arise and some pro/con comparisons of using Alpine-based images.\n\nTo minimize image size, it's uncommon for additional related tools (such as `git` or `bash`) to be included in Alpine-based images. Using this image as a base, add the things you need in your own Dockerfile (see the [`alpine` image description](https://hub.docker.com/_/alpine/) for examples of how to install packages if you are unfamiliar).\n\n# License\n\nView [license information](http://www.gnu.org/licenses/lgpl.txt) for the software contained in this image.\n\n# Supported Docker versions\n\nThis image is officially supported on Docker version 1.12.2.\n\nSupport for older versions (down to 1.6) is provided on a best-effort basis.\n\nPlease see [the Docker installation documentation](https://docs.docker.com/installation/) for details on how to upgrade your Docker daemon.\n\n# User Feedback\n\n## Issues\n\nIf you have any problems with or questions about this image, please contact us through a [GitHub issue](https://github.com/SonarSource/docker-sonarqube/issues). If the issue is related to a CVE, please check for [a `cve-tracker` issue on the `official-images` repository first](https://github.com/docker-library/official-images/issues?q=label%3Acve-tracker).\n\nYou can also reach many of the official image maintainers via the `#docker-library` IRC channel on [Freenode](https://freenode.net).\n\n## Contributing\n\nYou are invited to contribute new features, fixes, or updates, large or small; we are always thrilled to receive pull requests, and do our best to process them as fast as we can.\n\nBefore you start to code, we recommend discussing your plans through a [GitHub issue](https://github.com/SonarSource/docker-sonarqube/issues), especially for more ambitious contributions. This gives other contributors a chance to point you in the right direction, give you feedback on your design, and help you find out if someone else is working on the same thing.\n\n## Documentation\n\nDocumentation for this image is stored in the [`sonarqube/` directory](https://github.com/docker-library/docs/tree/master/sonarqube) of the [`docker-library/docs` GitHub repo](https://github.com/docker-library/docs). Be sure to familiarize yourself with the [repository's `README.md` file](https://github.com/docker-library/docs/blob/master/README.md) before attempting a pull request.",
  "type": "docker",
  "docker_name": "sonarqube",
  "revision": "6.1-alpine",
  "uris": [
    "https://hub.docker.com/r/_/sonarqube",
    "https://hub.docker.com/v2/repositories/library/sonarqube"
  ],
  "labels": [
    "Docker",
    "Binding/Region/North America/US"
  ],
  "info_url": "https://hub.docker.com/r/_/sonarqube",
  "requires": [
    {
      "kind": "host",
      "label": "Docker Engine"
    }
  ],
  "latest": true,
  "gatherbase_origin": "docker-hub"
}