{
  "dockerhub": {
    "web_url": "https://hub.docker.com/r/_/ubuntu-upstart",
    "repository_url": "https://hub.docker.com/v2/repositories/library/ubuntu-upstart",
    "tags_url": "https://hub.docker.com/v2/repositories/library/ubuntu-upstart/tags",
    "user": "library",
    "name": "ubuntu-upstart",
    "namespace": "library",
    "status": 1,
    "is_private": false,
    "is_automated": false,
    "star_count": 67,
    "pull_count": 236148,
    "last_updated": "2016-04-04T21:21:19.946273Z",
    "permissions": {
      "read": true,
      "write": false,
      "admin": false
    },
    "tags": [
      {
        "name": "utopic",
        "full_size": 104240606,
        "id": 13031,
        "repository": 8887,
        "creator": 7,
        "last_updater": 213249,
        "last_updated": "2016-04-04T21:21:20.252720Z",
        "image_id": null,
        "v2": true,
        "platforms": []
      },
      {
        "name": "14.10",
        "full_size": 104240606,
        "id": 13023,
        "repository": 8887,
        "creator": 7,
        "last_updater": 213249,
        "last_updated": "2016-04-04T21:21:10.616332Z",
        "image_id": null,
        "v2": true,
        "platforms": []
      },
      {
        "name": "latest",
        "full_size": 101694559,
        "id": 13029,
        "repository": 8887,
        "creator": 7,
        "last_updater": 213249,
        "last_updated": "2016-04-04T21:20:57.228671Z",
        "image_id": null,
        "v2": true,
        "platforms": []
      },
      {
        "name": "trusty",
        "full_size": 101694559,
        "id": 13010,
        "repository": 8887,
        "creator": 7,
        "last_updater": 213249,
        "last_updated": "2016-04-04T21:20:47.593362Z",
        "image_id": null,
        "v2": true,
        "platforms": []
      },
      {
        "name": "14.04",
        "full_size": 101694559,
        "id": 13018,
        "repository": 8887,
        "creator": 7,
        "last_updater": 213249,
        "last_updated": "2016-04-04T21:20:38.095684Z",
        "image_id": null,
        "v2": true,
        "platforms": []
      },
      {
        "name": "precise",
        "full_size": 78920203,
        "id": 13002,
        "repository": 8887,
        "creator": 7,
        "last_updater": 213249,
        "last_updated": "2016-04-04T21:20:26.117266Z",
        "image_id": null,
        "v2": true,
        "platforms": []
      },
      {
        "name": "12.04",
        "full_size": 78920203,
        "id": 13021,
        "repository": 8887,
        "creator": 7,
        "last_updater": 213249,
        "last_updated": "2016-04-04T21:20:16.511215Z",
        "image_id": null,
        "v2": true,
        "platforms": []
      },
      {
        "name": "saucy",
        "full_size": 75931710,
        "id": 13004,
        "repository": 8887,
        "creator": 7,
        "last_updater": 134455,
        "last_updated": "2015-11-14T15:57:05.854760Z",
        "image_id": null,
        "v2": true,
        "platforms": []
      },
      {
        "name": "quantal",
        "full_size": 66485298,
        "id": 13032,
        "repository": 8887,
        "creator": 7,
        "last_updater": 134455,
        "last_updated": "2015-11-14T15:56:55.335118Z",
        "image_id": null,
        "v2": true,
        "platforms": []
      },
      {
        "name": "raring",
        "full_size": 72452386,
        "id": 13014,
        "repository": 8887,
        "creator": 7,
        "last_updater": 134455,
        "last_updated": "2015-11-14T15:56:44.871592Z",
        "image_id": null,
        "v2": true,
        "platforms": []
      }
    ]
  },
  "docker_image": "ubuntu-upstart",
  "name": "ubuntu-upstart Docker container",
  "description": "Upstart is an event-based replacement for the /sbin/init daemon which starts processes at boot",
  "readme": "# **DEPRECATED**\n\nThis image is officially deprecated (especially now that Upstart is no longer the default init system for Ubuntu) and will receive no further updates. Please adjust your usage accordingly.\n\n# Supported tags and respective `Dockerfile` links\n\n-\t[`12.04`, `precise` (*sbin-init/ubuntu/upstart/12.04/Dockerfile*)](https://github.com/tianon/dockerfiles/blob/4d24a12b54b75b3e0904d8a285900d88d3326361/sbin-init/ubuntu/upstart/12.04/Dockerfile)\n-\t[`14.04`, `trusty`, `latest` (*sbin-init/ubuntu/upstart/14.04/Dockerfile*)](https://github.com/tianon/dockerfiles/blob/4d24a12b54b75b3e0904d8a285900d88d3326361/sbin-init/ubuntu/upstart/14.04/Dockerfile)\n-\t[`14.10`, `utopic` (*sbin-init/ubuntu/upstart/14.10/Dockerfile*)](https://github.com/tianon/dockerfiles/blob/4d24a12b54b75b3e0904d8a285900d88d3326361/sbin-init/ubuntu/upstart/14.10/Dockerfile)\n\n[![](https://badge.imagelayers.io/ubuntu-upstart:latest.svg)](https://imagelayers.io/?images=ubuntu-upstart:12.04,ubuntu-upstart:14.04,ubuntu-upstart:14.10)\n\nFor more information about this image and its history, please see [the relevant manifest file (`library/ubuntu-upstart`)](https://github.com/docker-library/official-images/blob/master/library/ubuntu-upstart). This image is updated via [pull requests to the `docker-library/official-images` GitHub repo](https://github.com/docker-library/official-images/pulls?q=label%3Alibrary%2Fubuntu-upstart).\n\nFor detailed information about the virtual/transfer sizes and individual layers of each of the above supported tags, please see [the `ubuntu-upstart/tag-details.md` file](https://github.com/docker-library/docs/blob/master/ubuntu-upstart/tag-details.md) in [the `docker-library/docs` GitHub repo](https://github.com/docker-library/docs).\n\n# What is Upstart?\n\nUpstart is an event-based replacement for the traditional init daemon – the method by which several Unix-like computer operating systems perform tasks when the computer is started. It was written by Scott James Remnant, a former employee of Canonical Ltd.\n\n> [wikipedia.org/wiki/Upstart](https://en.wikipedia.org/wiki/Upstart)\n\n![logo](https://raw.githubusercontent.com/docker-library/docs/9a6eb1db57c8882706a010edb9d340045029382a/ubuntu-upstart/logo.png)\n\n# Supported Docker versions\n\nThis image is officially supported on Docker version 1.11.2.\n\nSupport for older versions (down to 1.6) is provided on a best-effort basis.\n\nPlease see [the Docker installation documentation](https://docs.docker.com/installation/) for details on how to upgrade your Docker daemon.\n\n# User Feedback\n\n## Documentation\n\nDocumentation for this image is stored in the [`ubuntu-upstart/` directory](https://github.com/docker-library/docs/tree/master/ubuntu-upstart) of the [`docker-library/docs` GitHub repo](https://github.com/docker-library/docs). Be sure to familiarize yourself with the [repository's `REAMDE.md` file](https://github.com/docker-library/docs/blob/master/README.md) before attempting a pull request.\n\n## Issues\n\nThis image is provided on an as-is basis. If problems with it are discovered, they can be discussed in the `#docker-library` IRC channel on [Freenode](https://freenode.net), but any support will be best-effort.",
  "type": "docker",
  "docker_name": "ubuntu-upstart",
  "revision": "utopic",
  "uris": [
    "https://hub.docker.com/r/_/ubuntu-upstart",
    "https://hub.docker.com/v2/repositories/library/ubuntu-upstart"
  ],
  "labels": [
    "Docker",
    "Type/Infrastructure/Operating System/Linux/Ubuntu"
  ],
  "info_url": "https://hub.docker.com/r/_/ubuntu-upstart",
  "requires": [
    {
      "kind": "host",
      "label": "Docker Engine"
    }
  ],
  "latest": true,
  "gatherbase_origin": "docker-hub"
}