{
  "name": "application_just_nodejs Chef cookbook",
  "chef_cookbook_name": "application_just_nodejs",
  "revision": "0.0.1",
  "uris": [
    "https://supermarket.chef.io/cookbooks/application_just_nodejs",
    "https://supermarket.chef.io/cookbooks/application_just_nodejs/download",
    "https://supermarket.chef.io/cookbooks/application_just_nodejs/versions/0.0.1",
    "https://supermarket.chef.io/cookbooks/application_just_nodejs/versions/0.0.1/download",
    "https://supermarket.chef.io/api/v1/cookbooks/application_just_nodejs/versions/0.0.1",
    "https://supermarket.chef.io/api/v1/cookbooks/application_just_nodejs",
    "https://supermarket.chef.io/api/v1/cookbooks/application_just_nodejs/versions/0.0.1/download"
  ],
  "labels": [
    "Chef cookbook",
    "Other",
    "Executable/Script/Chef Cookbook",
    "Type/Middleware/Runtime/JavaScript/Node.js",
    "Binding/Region/North America/US",
    "Mode/Executable/Script/Chef Cookbook",
    "Style/Virtualization Level/Application"
  ],
  "info_url": "https://supermarket.chef.io/cookbooks/application_just_nodejs",
  "package_url": "https://supermarket.chef.io/api/v1/cookbooks/application_just_nodejs/versions/0.0.1/download",
  "deprecated": true,
  "created": "2014-09-10T10:46:05.090Z",
  "updated": "2015-12-11T16:47:47.627Z",
  "description": "Deploys and configures node.js-based applications",
  "maintainer": {
    "name": "256dpi",
    "email": "YOUR_EMAIL"
  },
  "license": "MIT",
  "chef_foodcritic_failure": true,
  "chef_up_for_adoption": null,
  "rating": null,
  "followers_count": 0,
  "downloads_count": 951956,
  "downloads_count_revision": 951956,
  "chef_replacement": {
    "url": "https://supermarket.chef.io/api/v1/cookbooks/application_nodejs"
  },
  "latest": true,
  "gatherbase_origin": "chef-supermarket",
  "readme_name": "README.md",
  "requires": [
    {
      "kind": "env",
      "uri": "https://supermarket.chef.io/cookbooks/application",
      "revision": "~> 4.0",
      "self_resolve": true
    }
  ]
}