{
  "name": "baryon Chef cookbook",
  "chef_cookbook_name": "baryon",
  "revision": "0.1.1",
  "uris": [
    "https://supermarket.chef.io/cookbooks/baryon",
    "https://supermarket.chef.io/cookbooks/baryon/download",
    "https://supermarket.chef.io/cookbooks/baryon/versions/0.1.1",
    "https://supermarket.chef.io/cookbooks/baryon/versions/0.1.1/download",
    "https://supermarket.chef.io/api/v1/cookbooks/baryon/versions/0.1.1",
    "https://supermarket.chef.io/api/v1/cookbooks/baryon",
    "https://supermarket.chef.io/api/v1/cookbooks/baryon/versions/0.1.1/download"
  ],
  "labels": [
    "Chef cookbook",
    "Utilities",
    "Executable/Script/Chef Cookbook",
    "Mode/Executable/Script/Chef Cookbook"
  ],
  "info_url": "https://supermarket.chef.io/cookbooks/baryon",
  "package_url": "https://supermarket.chef.io/api/v1/cookbooks/baryon/versions/0.1.1/download",
  "deprecated": false,
  "created": "2016-01-19T02:01:00.799Z",
  "updated": "2016-01-28T04:12:56.736Z",
  "description": "Installs/Configures baryon",
  "maintainer": {
    "name": "kisoku",
    "email": "msf@kisoku.net"
  },
  "license": "apache2",
  "chef_foodcritic_failure": false,
  "chef_up_for_adoption": null,
  "rating": null,
  "followers_count": 0,
  "downloads_count": 689,
  "downloads_count_revision": 217,
  "repository_url": "https://github.com/kisoku/baryon-cookbook",
  "issues_url": "https://github.com/kisoku/baryon-cookbook/issues",
  "chef_source_url": "https://github.com/kisoku/baryon-cookbook",
  "gatherbase_origin": "chef-supermarket",
  "readme_name": "README.md",
  "readme": "Installs/Configures baryon",
  "requires": [
    {
      "kind": "env",
      "uri": "https://supermarket.chef.io/cookbooks/poise-service",
      "revision": ">= 0.0.0",
      "self_resolve": true
    }
  ]
}