{
  "name": "bundler Chef cookbook",
  "chef_cookbook_name": "bundler",
  "revision": "0.2.0",
  "uris": [
    "https://supermarket.chef.io/cookbooks/bundler",
    "https://supermarket.chef.io/cookbooks/bundler/download",
    "https://supermarket.chef.io/cookbooks/bundler/versions/0.2.0",
    "https://supermarket.chef.io/cookbooks/bundler/versions/0.2.0/download",
    "https://supermarket.chef.io/api/v1/cookbooks/bundler/versions/0.2.0",
    "https://supermarket.chef.io/api/v1/cookbooks/bundler",
    "https://supermarket.chef.io/api/v1/cookbooks/bundler/versions/0.2.0/download"
  ],
  "labels": [
    "Chef cookbook",
    "Utilities",
    "Executable/Script/Chef Cookbook",
    "Mode/Executable/Script/Chef Cookbook",
    "Mode/Executable/Bundle"
  ],
  "info_url": "https://supermarket.chef.io/cookbooks/bundler",
  "package_url": "https://supermarket.chef.io/api/v1/cookbooks/bundler/versions/0.2.0/download",
  "deprecated": false,
  "created": "2010-02-06T01:54:44.000Z",
  "updated": "2010-02-06T01:54:45.000Z",
  "description": "Installs bundler and provides recipes to bundle actions",
  "maintainer": {
    "name": "jackhq",
    "email": "cookbooks@jackhq.com"
  },
  "license": "Apache 2.0",
  "chef_foodcritic_failure": null,
  "chef_up_for_adoption": null,
  "rating": null,
  "followers_count": 14,
  "downloads_count": 1277470,
  "downloads_count_revision": 1277470,
  "latest": true,
  "gatherbase_origin": "chef-supermarket",
  "readme_name": "README.md",
  "readme": "See Readme.md",
  "requires": [
    {
      "kind": "host",
      "label": "ubuntu",
      "revision": [],
      "one_of_group": "os"
    },
    {
      "kind": "host",
      "label": "debian",
      "revision": [],
      "one_of_group": "os"
    },
    {
      "kind": "env",
      "uri": "https://supermarket.chef.io/cookbooks/rubygems",
      "revision": [],
      "self_resolve": true
    }
  ],
  "chef_recipes": {
    "bundler": "unlock"
  },
  "parameters": {
    "bundler/app_path": {
      "default": "/home/ubuntu/apps",
      "calculated": false,
      "type": "string",
      "choice": [],
      "description": "Your Rack App Path",
      "display_name": "Application Path",
      "required": "optional",
      "recipes": [],
      "mapping": "cookbook_attribute"
    },
    "bundler/app": {
      "default": "my_app",
      "calculated": false,
      "type": "string",
      "choice": [],
      "description": "Your Rack App",
      "display_name": "Application Name",
      "required": "optional",
      "recipes": [],
      "mapping": "cookbook_attribute"
    }
  }
}