{
  "name": "fetchmail Chef cookbook",
  "chef_cookbook_name": "fetchmail",
  "revision": "1.0.1",
  "uris": [
    "https://supermarket.chef.io/cookbooks/fetchmail",
    "https://supermarket.chef.io/cookbooks/fetchmail/download",
    "https://supermarket.chef.io/cookbooks/fetchmail/versions/1.0.1",
    "https://supermarket.chef.io/cookbooks/fetchmail/versions/1.0.1/download",
    "https://supermarket.chef.io/api/v1/cookbooks/fetchmail/versions/1.0.1",
    "https://supermarket.chef.io/api/v1/cookbooks/fetchmail",
    "https://supermarket.chef.io/api/v1/cookbooks/fetchmail/versions/1.0.1/download"
  ],
  "labels": [
    "Chef cookbook",
    "Networking",
    "Executable/Script/Chef Cookbook",
    "Mode/Executable/Script/Chef Cookbook",
    "Type/Middleware/Email"
  ],
  "info_url": "https://supermarket.chef.io/cookbooks/fetchmail",
  "package_url": "https://supermarket.chef.io/api/v1/cookbooks/fetchmail/versions/1.0.1/download",
  "deprecated": false,
  "created": "2014-05-12T01:36:50.000Z",
  "updated": "2014-05-12T01:50:09.000Z",
  "description": "Installs/Configures Fetchmail",
  "maintainer": {
    "name": "brauliobo",
    "email": "braulio@eita.org.br"
  },
  "license": "GPLv3+",
  "chef_foodcritic_failure": null,
  "chef_up_for_adoption": null,
  "rating": null,
  "followers_count": 0,
  "downloads_count": 2528551,
  "downloads_count_revision": 1264366,
  "repository_url": "https://github.com/coletivoEITA/fetchmail-cookbook",
  "issues_url": "https://github.com/coletivoEITA/fetchmail-cookbook",
  "chef_source_url": "https://github.com/coletivoEITA/fetchmail-cookbook",
  "latest": true,
  "gatherbase_origin": "chef-supermarket",
  "readme_name": "README.md",
  "readme": "fetchmail Cookbook\n========================\nInstall fetchmail using the system package and configure\n\nRequirements\n------------\nPlataforms:\n - Debian\n - Ubuntu\n\nAttributes\n----------\n#### fetchmail::default\n<table>\n  <tr>\n    <th>Attribute</th>\n    <th>Description</th>\n    <th>Default</th>\n  </tr>\n  <tr>\n    <td><tt>node['fetchmail']['timeout']</tt></td>\n    <td>Interval to check for email</td>\n    <td><tt>20</tt></td>\n  </tr>\n  <tr>\n    <td><tt>node['fetchmail']['invisible']</tt></td>\n    <td>Toggle invisible option</td>\n    <td><tt>true</tt></td>\n  </tr>\n  <tr>\n    <td><tt>node['fetchmail']['no_bouncemail']</tt></td>\n    <td>Toggle no bouncemail option</td>\n    <td><tt>true</tt></td>\n  </tr>\n  <tr>\n    <td><tt>node['fetchmail']['syslog']</tt></td>\n    <td>Use syslog</td>\n    <td><tt>true</tt></td>\n  </tr>\n  <tr>\n    <td><tt>node['fetchmail']['logfile']</tt></td>\n    <td>Change log file location</td>\n    <td><tt>nil</tt></td>\n  </tr>\n  <tr>\n    <td><tt>node['fetchmail']['fetches']</tt></td>\n    <td>A list of emails to fetch, see below options</td>\n    <td><tt>[]</tt></td>\n  </tr>\n  <tr>\n    <td><tt>node['fetchmail']['fetches'][]['server']</tt></td>\n    <td>Email server domain</td>\n    <td><tt>mail.domain.com</tt></td>\n  </tr>\n  <tr>\n    <td><tt>node['fetchmail']['fetches'][]['protocol']</tt></td>\n    <td>Which protocol to use</td>\n    <td><tt>pop3</tt></td>\n  </tr>\n  <tr>\n    <td><tt>node['fetchmail']['fetches'][]['username']</tt></td>\n    <td>Username to login</td>\n    <td><tt>me@domain.com</tt></td>\n  </tr>\n  <tr>\n    <td><tt>node['fetchmail']['fetches'][]['password']</tt></td>\n    <td>Password to login</td>\n    <td><tt>a1b2c3</tt></td>\n  </tr>\n  <tr>\n    <td><tt>node['fetchmail']['fetches'][]['mda']</tt></td>\n    <td>Command to execute in MDA format</td>\n    <td><tt>echo</tt></td>\n  </tr>\n  <tr>\n    <td><tt>node['fetchmail']['fetches'][]['no_keep']</tt></td>\n    <td>Don't keep emails on the server</td>\n    <td><tt>false</tt></td>\n  </tr>\n</table>\n\nUsage\n-----\n#### fetchmail::default\nJust include `fetchmail` in your node's `run_list`:\n\n```json\n{\n  \"name\":\"my_node\",\n  \"run_list\": [\n    \"recipe[fetchmail]\"\n  ]\n}\n```\n\nContributing\n------------\n1. Fork the repository on Github\n2. Create a named feature branch (like `add_component_x`)\n3. Write your change\n4. Write tests for your change (if applicable)\n5. Run the tests, ensuring they all pass\n6. Submit a Pull Request using Github\n\n"
}