{
  "name": "minitest-handler Chef cookbook",
  "chef_cookbook_name": "minitest-handler",
  "revision": "0.0.4",
  "uris": [
    "https://supermarket.chef.io/cookbooks/minitest-handler",
    "https://supermarket.chef.io/cookbooks/minitest-handler/download",
    "https://supermarket.chef.io/cookbooks/minitest-handler/versions/0.0.4",
    "https://supermarket.chef.io/cookbooks/minitest-handler/versions/0.0.4/download",
    "https://supermarket.chef.io/api/v1/cookbooks/minitest-handler/versions/0.0.4",
    "https://supermarket.chef.io/api/v1/cookbooks/minitest-handler",
    "https://supermarket.chef.io/api/v1/cookbooks/minitest-handler/versions/0.0.4/download"
  ],
  "labels": [
    "Chef cookbook",
    "Other",
    "Executable/Script/Chef Cookbook",
    "Mode/Executable/Script/Chef Cookbook",
    "Type/Devopsware/Test"
  ],
  "info_url": "https://supermarket.chef.io/cookbooks/minitest-handler",
  "package_url": "https://supermarket.chef.io/api/v1/cookbooks/minitest-handler/versions/0.0.4/download",
  "deprecated": false,
  "created": "2012-03-01T08:49:53.000Z",
  "updated": "2015-10-26T00:02:23.887Z",
  "description": "Installs and configures minitest-chef-handler",
  "maintainer": {
    "name": "btm",
    "email": "btm@loftinjas.org"
  },
  "license": "Apache 2.0",
  "chef_foodcritic_failure": true,
  "chef_up_for_adoption": null,
  "rating": null,
  "followers_count": 11,
  "downloads_count": 33272004,
  "downloads_count_revision": 1254456,
  "gatherbase_origin": "chef-supermarket",
  "readme_name": "README.md",
  "readme": "Description\n===========\n\nThis cookbook utilizes the minitest-chef-handler project to facilitate cookbook testing.\n\nminitest-chef-handler project: https://github.com/calavera/minitest-chef-handler  \nstable minitest-handler cookbook: http://community.opscode.com/cookbook/minitest-handler  \nminitest-handler cookbook development: https://github.com/btm/minitest-handler-cookbook  \n\nRequirements\n============\n\nThe Opscode 'chef_handler' cookbook to allow the handler to be dynamically installed without modifying the client configuration\n\nAttributes\n==========\n\nnode[:minitest][:path] - Location to store and find tests\n\nUsage\n=====\n\n* The node run list should begin with 'recipe[chef_handler], recipe[chef-minitest]'\n* Each cookbook should contain tests in the 'files/default/tests/minitest' directory with a file suffix of '_test.rb'\n\nMinitest: https://github.com/seattlerb/minitest\n\nExample\n=====\n\n    class TestApache2 < MiniTest::Chef::TestCase\n      def test_that_the_package_installed\n        case node[:platform]\n        when \"ubuntu\",\"debian\"\n          assert system('apt-cache policy apache2 | grep Installed | grep -v none')\n        end\n      end\n    \n      def test_that_the_service_is_running\n        assert system('/etc/init.d/apache2 status')\n      end\n    \n      def test_that_the_service_is_enabled\n        assert File.exists?(Dir.glob(\"/etc/rc5.d/S*apache2\").first)\n      end\n    end\n\nChangelog\n=====\n\n### v0.0.4\n\nAdd examples/ top level directory (may not work)\n",
  "requires": [
    {
      "kind": "env",
      "uri": "https://supermarket.chef.io/cookbooks/chef_handler",
      "revision": ">= 0.0.0",
      "self_resolve": true
    }
  ]
}