{
  "name": "pygster Chef cookbook",
  "chef_cookbook_name": "pygster",
  "revision": "1.0.15",
  "uris": [
    "https://supermarket.chef.io/cookbooks/pygster",
    "https://supermarket.chef.io/cookbooks/pygster/download",
    "https://supermarket.chef.io/cookbooks/pygster/versions/1.0.15",
    "https://supermarket.chef.io/cookbooks/pygster/versions/1.0.15/download",
    "https://supermarket.chef.io/api/v1/cookbooks/pygster/versions/1.0.15",
    "https://supermarket.chef.io/api/v1/cookbooks/pygster",
    "https://supermarket.chef.io/api/v1/cookbooks/pygster/versions/1.0.15/download"
  ],
  "labels": [
    "Chef cookbook",
    "Networking",
    "Executable/Script/Chef Cookbook",
    "Mode/Executable/Script/Chef Cookbook"
  ],
  "info_url": "https://supermarket.chef.io/cookbooks/pygster",
  "package_url": "https://supermarket.chef.io/api/v1/cookbooks/pygster/versions/1.0.15/download",
  "deprecated": false,
  "created": "2014-05-12T22:58:43.000Z",
  "updated": "2015-10-23T17:43:37.400Z",
  "description": "Installs/Configures pygster",
  "maintainer": {
    "name": "ampledata",
    "email": "gba@onbeep.com"
  },
  "license": "Apache License, Version 2.0",
  "chef_foodcritic_failure": true,
  "chef_up_for_adoption": null,
  "rating": null,
  "followers_count": 0,
  "downloads_count": 3890048,
  "downloads_count_revision": 801270,
  "gatherbase_origin": "chef-supermarket",
  "readme_name": "README.md",
  "readme": "Installs/Configures pygster",
  "requires": [
    {
      "kind": "env",
      "uri": "https://supermarket.chef.io/cookbooks/python",
      "revision": ">= 0.0.0",
      "self_resolve": true
    }
  ]
}