{
  "name": "vmware-fusion Chef cookbook",
  "chef_cookbook_name": "vmware-fusion",
  "revision": "0.1.1",
  "uris": [
    "https://supermarket.chef.io/cookbooks/vmware-fusion",
    "https://supermarket.chef.io/cookbooks/vmware-fusion/download",
    "https://supermarket.chef.io/cookbooks/vmware-fusion/versions/0.1.1",
    "https://supermarket.chef.io/cookbooks/vmware-fusion/versions/0.1.1/download",
    "https://supermarket.chef.io/api/v1/cookbooks/vmware-fusion/versions/0.1.1",
    "https://supermarket.chef.io/api/v1/cookbooks/vmware-fusion",
    "https://supermarket.chef.io/api/v1/cookbooks/vmware-fusion/versions/0.1.1/download"
  ],
  "labels": [
    "Chef cookbook",
    "Other",
    "Executable/Script/Chef Cookbook",
    "Binding/Region/North America/US",
    "Mode/Executable/Script/Chef Cookbook"
  ],
  "info_url": "https://supermarket.chef.io/cookbooks/vmware-fusion",
  "package_url": "https://supermarket.chef.io/api/v1/cookbooks/vmware-fusion/versions/0.1.1/download",
  "deprecated": false,
  "created": "2015-07-29T06:09:22.172Z",
  "updated": "2016-01-29T19:19:18.200Z",
  "description": "Installs VMWare Fusion",
  "maintainer": {
    "name": "roboticcheese",
    "email": "j@p4nt5.com"
  },
  "license": "apache2",
  "chef_foodcritic_failure": false,
  "chef_up_for_adoption": null,
  "rating": null,
  "followers_count": 3,
  "downloads_count": 47090,
  "downloads_count_revision": 20194,
  "repository_url": "https://github.com/RoboticCheese/vmware-fusion-chef",
  "issues_url": "https://github.com/RoboticCheese/vmware-fusion-chef/issues",
  "chef_source_url": "https://github.com/RoboticCheese/vmware-fusion-chef",
  "gatherbase_origin": "chef-supermarket",
  "readme_name": "README.md",
  "readme": "Installs VMWare Fusion",
  "requires": [
    {
      "kind": "host",
      "label": "mac_os_x",
      "revision": ">= 0.0.0",
      "one_of_group": "os"
    },
    {
      "kind": "env",
      "uri": "https://supermarket.chef.io/cookbooks/dmg",
      "revision": "~> 2.2",
      "self_resolve": true
    }
  ]
}