{
  "name": "winlogbeat Chef cookbook",
  "chef_cookbook_name": "winlogbeat",
  "revision": "0.1.1",
  "uris": [
    "https://supermarket.chef.io/cookbooks/winlogbeat",
    "https://supermarket.chef.io/cookbooks/winlogbeat/download",
    "https://supermarket.chef.io/cookbooks/winlogbeat/versions/0.1.1",
    "https://supermarket.chef.io/cookbooks/winlogbeat/versions/0.1.1/download",
    "https://supermarket.chef.io/api/v1/cookbooks/winlogbeat/versions/0.1.1",
    "https://supermarket.chef.io/api/v1/cookbooks/winlogbeat",
    "https://supermarket.chef.io/api/v1/cookbooks/winlogbeat/versions/0.1.1/download"
  ],
  "labels": [
    "Chef cookbook",
    "Executable/Script/Chef Cookbook",
    "Mode/Executable/Script/Chef Cookbook",
    "Type/Devopsware/Logging"
  ],
  "info_url": "https://supermarket.chef.io/cookbooks/winlogbeat",
  "package_url": "https://supermarket.chef.io/api/v1/cookbooks/winlogbeat/versions/0.1.1/download",
  "deprecated": false,
  "created": "2016-06-24T11:26:20.863Z",
  "updated": "2016-08-08T14:17:21.104Z",
  "description": "Installs/Configures Elastic Winlogbeat",
  "maintainer": {
    "name": "anuriq",
    "email": "anuriq@gmail.com"
  },
  "license": "Apache 2.0",
  "chef_foodcritic_failure": false,
  "chef_up_for_adoption": null,
  "rating": null,
  "followers_count": 1,
  "downloads_count": 141,
  "downloads_count_revision": 80,
  "repository_url": "https://github.com/anuriq/chef-winlogbeat",
  "issues_url": "https://github.com/anuriq/chef-winlogbeat/issues",
  "chef_source_url": "https://github.com/anuriq/chef-winlogbeat",
  "latest": true,
  "gatherbase_origin": "chef-supermarket",
  "readme_name": "README.md",
  "readme": "# winlogbeat\n\n### Description\nElastic Winlogbeat is used to forward Windows event logs to elastic and/or logstash.\n\n### Requirements\n\n#### Platforms\nTested only on Windows Server 2012 R2.\n\n### Attributes\n|Attribute|Description|Type|Default|\n|---------|-----------|----|-------|\n|['winlogbeat']['version']|Version of Elastic Winlogbeat.|String|1.2.2|\n|['winlogbeat']['package_url']|Url to download Elastic Winlogbeat from.|String|auto|\n|['winlogbeat']['notify_restart']|Automatically restart Winlogbeat if config changes during converge.|Boolean|`true`|\n|['winlogbeat']['install_only']|If `true` do not create service and generate config file.|Boolean|`false`|\n|['winlogbeat']['install_dir']|Installation directory for Elastic Winlogbeat.|String|C:\\Program Files\\Winlogbeat|\n|['winlogbeat']['override_config']|Configuration values to override in default config.|Hash|{}|\n\n### Recipes\n\n* `default.rb` - Install and configure Elastic Winlogbeat.\n* `install.rb` - Download Winlogbeat.\n* `configure.rb` - Create a service and generate config file.\n\n\n### Kitchen\n```bash\n# check style\nchef exec rake style\n# converge and run tests\nchef exec rake integration:vagrant\n```\n\n### Examples\nFor examples see `test/shared/cookbooks/test` cookbook.\n\n### Authors\n* Author:: Azat Khadiev (anuriq@gmail.com)\n",
  "requires": [
    {
      "kind": "host",
      "label": "windows",
      "revision": ">= 0.0.0",
      "one_of_group": "os"
    }
  ]
}